AUTHORS.rst
CONTRIBUTING.rst
HISTORY.rst
LICENSE
MANIFEST.in
README.rst
setup.cfg
setup.py
docs/Makefile
docs/authors.rst
docs/conf.py
docs/contributing.rst
docs/history.rst
docs/index.rst
docs/installation.rst
docs/make.bat
docs/readme.rst
docs/usage.rst
polr/__init__.py
polr/cli.py
polr/polr.py
polr/settings.py
polr/utils.py
polr_py.egg-info/PKG-INFO
polr_py.egg-info/SOURCES.txt
polr_py.egg-info/dependency_links.txt
polr_py.egg-info/entry_points.txt
polr_py.egg-info/not-zip-safe
polr_py.egg-info/requires.txt
polr_py.egg-info/top_level.txt
tests/__init__.py
tests/test_polr.py