Metadata-Version: 1.1
Name: polr-py
Version: 0.3.3
Summary: Python CLI for the Polr link shortener
Home-page: https://github.com/kylie-a/polr-py
Author: Kylie Auld
Author-email: kylie.a@protonmail.com
License: MIT license
Keywords: polr
Platform: UNKNOWN
Classifier: Development Status :: 2 - Pre-Alpha
Classifier: Intended Audience :: Developers
Classifier: License :: OSI Approved :: MIT License
Classifier: Natural Language :: English
Classifier: Programming Language :: Python :: 2
Classifier: Programming Language :: Python :: 2.7
Classifier: Programming Language :: Python :: 3
Classifier: Programming Language :: Python :: 3.4
Classifier: Programming Language :: Python :: 3.5
Classifier: Programming Language :: Python :: 3.6
Classifier: Programming Language :: Python :: 3.7
